adip_calculator_unique/__init__.py
adip_calculator_unique/functions.py
adip_calculator_unique-0.1.1.dist-info/METADATA
adip_calculator_unique-0.1.1.dist-info/WHEEL
adip_calculator_unique-0.1.1.dist-info/RECORD
