Metadata-Version: 2.3
Name: adip-calculator-unique
Version: 0.1.1
Summary: Basic Calculator comprising 5 functionalities: + - % * /
License: MIT
Author: Aditya Pandey
Author-email: adityaadityapandey2002@gmail.com
Requires-Python: >=3.8
Classifier: License :: OSI Approved :: MIT License
Classifier: Programming Language :: Python :: 3
Classifier: Programming Language :: Python :: 3.8
Classifier: Programming Language :: Python :: 3.9
Classifier: Programming Language :: Python :: 3.10
Classifier: Programming Language :: Python :: 3.11
Classifier: Programming Language :: Python :: 3.12
Classifier: Programming Language :: Python :: 3.13
